diffpy/__init__.py
diffpy/utils/__init__.py
diffpy/utils/diffraction_objects.py
diffpy/utils/resampler.py
diffpy/utils/tools.py
diffpy/utils/transforms.py
diffpy/utils/validators.py
diffpy/utils/version.py
diffpy/utils/parsers/__init__.py
diffpy/utils/parsers/custom_exceptions.py
diffpy/utils/parsers/loaddata.py
diffpy/utils/parsers/serialization.py
diffpy/utils/wx/__init__.py
diffpy/utils/wx/gridutils.py
diffpy_utils-3.6.1.dist-info/licenses/AUTHORS.rst
diffpy_utils-3.6.1.dist-info/licenses/LICENSE.rst
diffpy_utils-3.6.1.dist-info/licenses/LICENSE_DANSE.txt
diffpy_utils-3.6.1.dist-info/METADATA
diffpy_utils-3.6.1.dist-info/WHEEL
diffpy_utils-3.6.1.dist-info/top_level.txt
diffpy_utils-3.6.1.dist-info/RECORD
