Metadata-Version: 2.4
Name: diffpy.utils
Version: 3.6.1
Summary: General utilities for analyzing diffraction data
Author-email: Simon Billinge <sb2896@columbia.edu>
Maintainer-email: Simon Billinge <sb2896@columbia.edu>
Project-URL: Homepage, https://github.com/diffpy/diffpy.utils/
Project-URL: Issues, https://github.com/diffpy/diffpy.utils/issues/
Keywords: text data parsers,wx grid,diffraction objects
Classifier: Development Status :: 5 - Production/Stable
Classifier: Environment :: Console
Classifier: Intended Audience :: Developers
Classifier: Intended Audience :: Science/Research
Classifier: License :: Free To Use But Restricted
Classifier: Operating System :: MacOS :: MacOS X
Classifier: Operating System :: Microsoft :: Windows
Classifier: Operating System :: POSIX
Classifier: Operating System :: Unix
Classifier: Programming Language :: Python :: 3.11
Classifier: Programming Language :: Python :: 3.12
Classifier: Programming Language :: Python :: 3.13
Classifier: Topic :: Scientific/Engineering :: Physics
Classifier: Topic :: Scientific/Engineering :: Chemistry
Requires-Python: <3.14,>=3.11
License-File: LICENSE.rst
License-File: LICENSE_DANSE.txt
License-File: AUTHORS.rst
Requires-Dist: numpy
Requires-Dist: xraydb
Requires-Dist: scipy
Dynamic: license-file
